core_validator-0.1.0.dist-info/METADATA
core_validator-0.1.0.dist-info/WHEEL
core_validator-0.1.0.dist-info/licenses/LICENSE
core_validator/__init__.py
core_validator/deprecated.py
core_validator/types.py
core_validator/utils.py
core_validator/validator.py
examples/__init__.py
examples/deprecated/multiple_error.py
examples/deprecated/single_error.py
examples/multiple_error.py
examples/single_error.py
examples/types.py
core_validator-0.1.0.dist-info/RECORD
