Metadata-Version: 2.1
Name: core-validator
Version: 0.1.0
Author-Email: maksyutov vlad <maksyutov.vlad@gmail.com>
License: MIT
Project-URL: Homepage, https://gitlab.com/pachek-opensource/validator/core-validator
Requires-Python: >=3.11
